setup.cfg
setup.py
wethepeopletoolkit/__init__.py
wethepeopletoolkit/choropleth.py
wethepeopletoolkit/cluster_evaluator.py
wethepeopletoolkit/clusterer.py
wethepeopletoolkit/data_importer.py
wethepeopletoolkit/downloader.py
wethepeopletoolkit/file_cleaner.py
wethepeopletoolkit/hive_checker.py
wethepeopletoolkit/main.py
wethepeopletoolkit/spark_starter.py
wethepeopletoolkit/sql_extractor.py
wethepeopletoolkit/state_processor.py
wethepeopletoolkit/top_petitions.py
wethepeopletoolkit/topic_extractor.py
wethepeopletoolkit/us_states.svg
wethepeopletoolkit.egg-info/PKG-INFO
wethepeopletoolkit.egg-info/SOURCES.txt
wethepeopletoolkit.egg-info/dependency_links.txt
wethepeopletoolkit.egg-info/entry_points.txt
wethepeopletoolkit.egg-info/requires.txt
wethepeopletoolkit.egg-info/top_level.txt