Metadata-Version: 1.1
Name: wethepeopletoolkit
Version: 1.6
Summary: A project for analyzing and visualizing data from the Obama-era 'We the People' petitions site.
Home-page: https://github.com/alexpeattie/wethepeopletoolkit
Author: Alex Peattie
Author-email: me@alexpeattie.com
License: MIT
Download-URL: https://github.com/alexpeattie/wethepeopletoolkit/archive/1.6.tar.gz
Keywords: wethepeople petitions datascience analysis
Platform: UNKNOWN
